plasmid_design/__init__.py
plasmid_design/constants.py
plasmid_design/drive.py
plasmid_design/idt_api.py
plasmid_design/plasmid_design.py
plasmid_design/sequence.py
plasmid_design/utils.py
plasmid_design-0.0.4.dist-info/LICENSE.txt
plasmid_design-0.0.4.dist-info/METADATA
plasmid_design-0.0.4.dist-info/WHEEL
plasmid_design-0.0.4.dist-info/entry_points.txt
plasmid_design-0.0.4.dist-info/top_level.txt
plasmid_design-0.0.4.dist-info/RECORD
