Metadata-Version: 2.1
Name: plasmid-design
Version: 0.0.4
Summary: Automated plasmid design from speadsheet specification
Author: David Feldman
License: Copyright (c) 2022 David Feldman
Project-URL: Homepage, https://github.com/feldman4/plasmid-design
Project-URL: Bug Tracker, https://github.com/feldman4/plasmid-design/issues
Keywords: plasmid,vector,design,DNA
Classifier: Programming Language :: Python :: 3
Classifier: License :: OSI Approved :: MIT License
Classifier: Operating System :: OS Independent
Requires-Python: >=3.7
License-File: LICENSE.txt
Requires-Dist: dnachisel
Requires-Dist: fire
Requires-Dist: joblib
Requires-Dist: natsort
Requires-Dist: python-slugify
Requires-Dist: pandas
Requires-Dist: pygsheets
Requires-Dist: pyyaml
